ispammer/__init__.py
ispammer/api.py
ispammer/ispammer.py
ispammer-2.0.dist-info/METADATA
ispammer-2.0.dist-info/WHEEL
ispammer-2.0.dist-info/entry_points.txt
ispammer-2.0.dist-info/top_level.txt
ispammer-2.0.dist-info/RECORD
