Metadata-Version: 2.1
Name: ispammer
Version: 2.0
Summary: A Free & Open Source Tool for Call/SMS Bombing on Indian Number 
Home-page: https://github.com/MrSp4rX/iSpammer
Author: MrSp4rX
Author-email: sparkykalund@gmail.com
License: GPL
Download-URL: https://github.com/MrSp4rX/iSpammer/archive/module.zip
Keywords: android,spam,sms,bomb,termux,sms-bomber,bomber,sms-bomb,bombing,call-bomb,ispammmer,mrsp4rx,indian-bombing,call-bombing
Platform: UNKNOWN
Requires-Python: >=3.5
Requires-Dist: requests
